mctest/__init__.py
mctest/api.py
mctest-0.0.2.dist-info/LICENSE
mctest-0.0.2.dist-info/METADATA
mctest-0.0.2.dist-info/WHEEL
mctest-0.0.2.dist-info/top_level.txt
mctest-0.0.2.dist-info/RECORD
