Metadata-Version: 2.1
Name: mctest
Version: 0.0.2
Summary: 程序员的战争
Home-page: https://github.com/HGzhao/MagCore_GameClient
Author: Miracle
Author-email: miracleyoung0723@gmail.com
License: MIT
Platform: UNKNOWN
Classifier: Topic :: Games/Entertainment 
Classifier: Topic :: Games/Entertainment :: Puzzle Games
Classifier: Topic :: Games/Entertainment :: Board Games
Classifier: Topic :: Software Development :: Libraries :: Python Modules
Classifier: Programming Language :: Python
Classifier: Programming Language :: Python :: 3
Classifier: Programming Language :: Python :: 3.5
Classifier: Programming Language :: Python :: 3.6
Classifier: Programming Language :: Python :: 3.7
Classifier: Programming Language :: Python :: Implementation :: CPython
Requires-Dist: requests
